croniter/__init__.py
croniter/croniter.py
dt_croniter-6.0.1.dist-info/LICENSE
dt_croniter-6.0.1.dist-info/METADATA
dt_croniter-6.0.1.dist-info/WHEEL
dt_croniter-6.0.1.dist-info/top_level.txt
dt_croniter-6.0.1.dist-info/RECORD
